MANIFEST.in
README.rst
setup.cfg
setup.py
pdown/__init__.py
pdown/cli.py
pdown/commands/__init__.py
pdown/commands/base.py
pdown/commands/chart.py
pdown/commands/edit.py
tests/charts.txt
tests/test_cli.py
tests/commands/test_hello.py