Metadata-Version: 1.1
Name: pdown
Version: 1.0.5
Summary: A command line program to download/manipulate periscope data
Home-page: UNKNOWN
Author: Stephen Cockerill
Author-email: scockerill@luciddg.com
License: UNLICENSE
Keywords: cli
Platform: UNKNOWN
Classifier: Natural Language :: English
Classifier: Operating System :: OS Independent
Classifier: Programming Language :: Python :: 2.7
